{
    "cp": {
        "username": "RustTest000",
        "password": "RustyRustRustRust",
        "vendor": "RustVendor",
        "model": "RustModel",
        "serial": "RustTest000",
        "protocol": "ocpp1.6",
        "base_url": "ws://127.0.0.1:8180/steve/websocket/CentralSystemService/"
    },
    "events": [
        {
            "duration": 2,
            "event": {
                "Authorize": {
                    "RFID": {
                        "id_tag": "TAG123"
                    }
                }
            }
        },
        {
            "duration": 2,
            "event": "CommunicationStop"
        },
        {
            "duration": 10,
            "event": "CommunicationStart"
        },
        {
            "duration": 2,
            "event": {
                "Authorize": {
                    "RFID": {
                        "id_tag": "TAG123"
                    }
                }
            }
        },
        {
            "duration": 2,
            "event": {
                "Plug": [
                    {
                        "evse_index": 1,
                        "connector_id": 1
                    },
                    {
                        "power_vs_soc": [
                            [0.0, 50.0],
                            [20.0, 105.0],
                            [80.0, 105.0],
                            [100.0, 2.0]
                        ],
                        "soc": 20.0,
                        "final_soc": 80.0,
                        "capacity": 88.0,
                        "power": 0.0
                    }
                ]
            }
        },
        {
            "duration": 60,
            "event": {
                "Unplug": {
                    "evse_index": 1,
                    "connector_id": 1
                }
            }
        }
    ],
    "components": [
        {
            "instance": null,
            "name": "AlignedDataCtrlr",
            "evse": null,
            "connector": null,
            "variables": [
                {
                    "instance": null,
                    "name": "Interval",
                    "ocpp16_key": "MeterValueSampleInterval",
                    "value": null,
                    "required": true,
                    "attributes": {
                        "mutability": "ReadWrite",
                        "type": null
                    },
                    "characteristics": {
                        "data_type": "integer",
                        "unit": "s",
                        "values_list": null,
                        "max_limit": null,
                        "min_limit": null
                    },
                    "used": null,
                    "default_value": 15
                }
            ]
        },
        {
            "instance": null,
            "name": "OCPPCommCtrlr",
            "evse": null,
            "connector": null,
            "variables": [
                {
                    "instance": null,
                    "name": "HeartbeatInterval",
                    "ocpp16_key": "HeartbeatInterval",
                    "value": null,
                    "required": false,
                    "attributes": {
                        "mutability": "ReadWrite",
                        "type": null
                    },
                    "characteristics": {
                        "data_type": "integer",
                        "unit": "s",
                        "values_list": null,
                        "max_limit": null,
                        "min_limit": 1
                    },
                    "used": null,
                    "default_value": "120"
                },
                {
                    "instance": null,
                    "name": "NetworkConfigurationPriority",
                    "ocpp16_key": "CpoName",
                    "value": null,
                    "required": true,
                    "attributes": {
                        "mutability": "ReadWrite",
                        "type": "Actual"
                    },
                    "characteristics": {
                        "data_type": "SequenceList",
                        "unit": null,
                        "values_list": "Network1",
                        "max_limit": null,
                        "min_limit": null
                    },
                    "used": null,
                    "default_value": "Network1"
                }
            ]
        },
        {
            "instance": "EVSE 1",
            "name": "EVSE",
            "evse": 1,
            "connector": null,
            "variables": []
        },
        {
            "instance": null,
            "name": "Connector",
            "evse": 1,
            "connector": 1,
            "variables": []
        }
    ]
}